celeste_google/__init__.py
celeste_google/auth.py
celeste_google/py.typed
celeste_google/cloud_tts/__init__.py
celeste_google/cloud_tts/client.py
celeste_google/cloud_tts/config.py
celeste_google/cloud_tts/parameters.py
celeste_google/generate_content/__init__.py
celeste_google/generate_content/client.py
celeste_google/generate_content/config.py
celeste_google/generate_content/parameters.py
celeste_google/generate_content/streaming.py
celeste_google/imagen/__init__.py
celeste_google/imagen/client.py
celeste_google/imagen/config.py
celeste_google/imagen/parameters.py
celeste_google/veo/__init__.py
celeste_google/veo/client.py
celeste_google/veo/config.py
celeste_google/veo/parameters.py
celeste_google-0.3.6.dist-info/METADATA
celeste_google-0.3.6.dist-info/WHEEL
celeste_google-0.3.6.dist-info/entry_points.txt
celeste_google-0.3.6.dist-info/RECORD
