Metadata-Version: 2.4
Name: celeste-google
Version: 0.3.6
Summary: Google (Gemini API) provider package for Celeste AI
Author-email: Kamilbenkirane <kamil@withceleste.ai>
License: Apache-2.0
Requires-Python: >=3.12
Requires-Dist: celeste-ai
Requires-Dist: google-auth
Requires-Dist: httpx
Requires-Dist: requests
